spokes/__init__.py
spokes/download_databank.py
spokes/run_simulation.py
spokes/pipeline/A_Setup.py
spokes/pipeline/B_SelectTargets.py
spokes/pipeline/C_TileSurvey.py
spokes/pipeline/D_AllocateFibers.py
spokes/pipeline/H_MeasureSpectroscopicRedshift.py
spokes/pipeline/I_BinRedshift.py
spokes/pipeline/J_CalculateSelectionFunction.py
spokes/pipeline/__init__.py
spokes/utils/__init__.py
spokes/utils/logger.py
spokes-0.1.0.dist-info/LICENSE
spokes-0.1.0.dist-info/METADATA
spokes-0.1.0.dist-info/WHEEL
spokes-0.1.0.dist-info/top_level.txt
spokes-0.1.0.dist-info/RECORD
