Metadata-Version: 2.1
Name: spokes
Version: 0.1.0
Summary: An End-to-End Simulation Facility for Spectroscopic Cosmological Surveys
Home-page: https://github.com/deepskies/spokes
Author: Taig Singh
Author-email: taig.singh@gmail.com
Maintainer: Taig Singh
Maintainer-email: taig.singh@gmail.com
License: UNKNOWN
Project-URL: Bug Tracker, https://github.com/deepskies/spokes/issues
Project-URL: Source Code, https://github.com/deepskies/spokes
Platform: UNKNOWN
Classifier: Development Status :: 2 - Pre-Alpha
Classifier: Intended Audience :: Science/Research
Classifier: Programming Language :: Python :: 3
Classifier: License :: OSI Approved :: Apache Software License
Classifier: Operating System :: OS Independent
Classifier: Topic :: Scientific/Engineering :: Astronomy
Classifier: Topic :: Scientific/Engineering :: Physics
Requires-Dist: numpy
Requires-Dist: h5py
Requires-Dist: pyyaml
Provides-Extra: data
Requires-Dist: dropbox ; extra == 'data'
